pubmed_scraper/__init__.py
pubmed_scraper/api.py
pubmed_scraper/cli/main.py
pubmed_scraper/parser.py
pubmed_scraper/writer.py
pubmed_scraper_rashi-0.1.3.dist-info/entry_points.txt
pubmed_scraper_rashi-0.1.3.dist-info/METADATA
pubmed_scraper_rashi-0.1.3.dist-info/WHEEL
pubmed_scraper_rashi-0.1.3.dist-info/RECORD
