Metadata-Version: 2.3
Name: pubmed-scraper-rashi
Version: 0.1.3
Summary: Fetch PubMed papers with non-academic authors
Author: Rashi Jain
Author-email: rjrashijain2709@gmail.com
Requires-Python: >=3.9
Classifier: Programming Language :: Python :: 3
Classifier: Programming Language :: Python :: 3.9
Classifier: Programming Language :: Python :: 3.10
Classifier: Programming Language :: Python :: 3.11
Classifier: Programming Language :: Python :: 3.12
Classifier: Programming Language :: Python :: 3.13
Requires-Dist: requests (>=2.32.4)
Project-URL: Repository, https://github.com/Rashijain2709/pubmed-scraper
